tracardi_string_validator/plugin.py
tracardi_string_validator/model/__init__.py
tracardi_string_validator/model/configuration.py
tracardi_string_validator/model/__pycache__/__init__.cpython-38.pyc
tracardi_string_validator/model/__pycache__/configuration.cpython-38.pyc
tracardi_string_validator/service/__init__.py
tracardi_string_validator/service/validator.py
tracardi_string_validator/service/__pycache__/__init__.cpython-38.pyc
tracardi_string_validator/service/__pycache__/validator.cpython-38.pyc
tracardi_string_validator/test/test_manual.py
tracardi_string_validator/test/test_plugin_validator.py
tracardi_string_validator-0.6.0.dist-info/LICENSE.md
tracardi_string_validator-0.6.0.dist-info/METADATA
tracardi_string_validator-0.6.0.dist-info/WHEEL
tracardi_string_validator-0.6.0.dist-info/top_level.txt
tracardi_string_validator-0.6.0.dist-info/RECORD
