Metadata-Version: 2.1
Name: tracardi-string-validator
Version: 0.6.0
Summary: The purpose of this plugin is validate data.
Home-page: UNKNOWN
Author: Patryk Migaj
Author-email: patromi123@gmail.com
License: UNKNOWN
Keywords: tracardi,plugin
Platform: UNKNOWN
Classifier: Programming Language :: Python :: 3
Classifier: License :: OSI Approved :: MIT License
Classifier: Operating System :: OS Independent
Requires-Python: >=3.8
License-File: LICENSE.md
Requires-Dist: tracardi-plugin-sdk (>=0.6.22)
Requires-Dist: pydantic
Requires-Dist: tracardi-dot-notation
Requires-Dist: barcodenumber
